<?xml version="1.0" encoding="utf-8"?>
<MyNewCollectionOfStringAnimal>
  <Capacity>10</Capacity>
  <Items>
    <Point>
      <Key>1</Key>
      <Value>
        <Artiodactyl xmlns:xsi="http://www.w3.org/2001/XMLSchema-instance" xmlns:xsd="http://www.w3.org/2001/XMLSchema">
          <Weight>74</Weight>
          <Height>3</Height>
          <Age>4</Age>
          <Name>Джеси</Name>
          <Note>none</Note>
          <Specie>Бизон</Specie>
          <Location>Южная Америка</Location>
          <LivingEnvironment>Наземно-воздушная</LivingEnvironment>
          <Lifestyle>Дневной</Lifestyle>
          <HoofSize>4</HoofSize>
          <HornsSize>9</HornsSize>
        </Artiodactyl>
      </Value>
    </Point>
    <Point>
      <Key>2</Key>
      <Value>
        <Mammal xmlns:xsi="http://www.w3.org/2001/XMLSchema-instance" xmlns:xsd="http://www.w3.org/2001/XMLSchema">
          <Weight>88</Weight>
          <Height>3</Height>
          <Age>82</Age>
          <Name>Герда</Name>
          <Note>none</Note>
          <Specie>Кит</Specie>
          <Location>Европа</Location>
          <LivingEnvironment>Водная</LivingEnvironment>
          <Lifestyle>Дневной</Lifestyle>
        </Mammal>
      </Value>
    </Point>
    <Point>
      <Key>8</Key>
      <Value>
        <Mammal xmlns:xsi="http://www.w3.org/2001/XMLSchema-instance" xmlns:xsd="http://www.w3.org/2001/XMLSchema">
          <Weight>16</Weight>
          <Height>1</Height>
          <Age>15</Age>
          <Name>Багира</Name>
          <Note>none</Note>
          <Specie>Волк</Specie>
          <Location>Европа</Location>
          <LivingEnvironment>Наземно-воздушная</LivingEnvironment>
          <Lifestyle>Дневной</Lifestyle>
        </Mammal>
      </Value>
    </Point>
    <Point>
      <Key>3</Key>
      <Value>
        <Animal xmlns:xsi="http://www.w3.org/2001/XMLSchema-instance" xmlns:xsd="http://www.w3.org/2001/XMLSchema">
          <Weight>33</Weight>
          <Height>4</Height>
          <Age>81</Age>
          <Name>Хатико</Name>
          <Note>none</Note>
        </Animal>
      </Value>
    </Point>
    <Point>
      <Key>9</Key>
      <Value>
        <Artiodactyl xmlns:xsi="http://www.w3.org/2001/XMLSchema-instance" xmlns:xsd="http://www.w3.org/2001/XMLSchema">
          <Weight>2</Weight>
          <Height>5</Height>
          <Age>25</Age>
          <Name>Грай</Name>
          <Note>none</Note>
          <Specie>Антилопа </Specie>
          <Location>Европа</Location>
          <LivingEnvironment>Наземно-воздушная</LivingEnvironment>
          <Lifestyle>Дневной</Lifestyle>
          <HoofSize>1</HoofSize>
          <HornsSize>9</HornsSize>
        </Artiodactyl>
      </Value>
    </Point>
    <Point>
      <Key>4</Key>
      <Value>
        <Animal xmlns:xsi="http://www.w3.org/2001/XMLSchema-instance" xmlns:xsd="http://www.w3.org/2001/XMLSchema">
          <Weight>11</Weight>
          <Height>3</Height>
          <Age>54</Age>
          <Name>Джеси</Name>
          <Note>none</Note>
        </Animal>
      </Value>
    </Point>
    <Point>
      <Key>5</Key>
      <Value>
        <Artiodactyl xmlns:xsi="http://www.w3.org/2001/XMLSchema-instance" xmlns:xsd="http://www.w3.org/2001/XMLSchema">
          <Weight>67</Weight>
          <Height>1</Height>
          <Age>29</Age>
          <Name>Гром</Name>
          <Note>none</Note>
          <Specie>Бизон</Specie>
          <Location>Европа</Location>
          <LivingEnvironment>Наземно-воздушная</LivingEnvironment>
          <Lifestyle>Дневной</Lifestyle>
          <HoofSize>4</HoofSize>
          <HornsSize>1</HornsSize>
        </Artiodactyl>
      </Value>
    </Point>
    <Point>
      <Key>6</Key>
      <Value>
        <Artiodactyl xmlns:xsi="http://www.w3.org/2001/XMLSchema-instance" xmlns:xsd="http://www.w3.org/2001/XMLSchema">
          <Weight>26</Weight>
          <Height>3</Height>
          <Age>65</Age>
          <Name>Макс</Name>
          <Note>none</Note>
          <Specie>Бегемот</Specie>
          <Location>Антарктида</Location>
          <LivingEnvironment>Наземно-воздушная</LivingEnvironment>
          <Lifestyle>Дневной</Lifestyle>
          <HoofSize>3</HoofSize>
          <HornsSize>6</HornsSize>
        </Artiodactyl>
      </Value>
    </Point>
    <Point>
      <Key>7</Key>
      <Value>
        <Mammal xmlns:xsi="http://www.w3.org/2001/XMLSchema-instance" xmlns:xsd="http://www.w3.org/2001/XMLSchema">
          <Weight>26</Weight>
          <Height>4</Height>
          <Age>69</Age>
          <Name>Грай</Name>
          <Note>none</Note>
          <Specie>Собака</Specie>
          <Location>Европа</Location>
          <LivingEnvironment>Наземно-воздушная</LivingEnvironment>
          <Lifestyle>Дневной</Lifestyle>
        </Mammal>
      </Value>
    </Point>
    <Point>
      <Key>10</Key>
      <Value>
        <Artiodactyl xmlns:xsi="http://www.w3.org/2001/XMLSchema-instance" xmlns:xsd="http://www.w3.org/2001/XMLSchema">
          <Weight>15</Weight>
          <Height>1</Height>
          <Age>43</Age>
          <Name>Боня</Name>
          <Note>none</Note>
          <Specie>Антилопа </Specie>
          <Location>Северная Америка</Location>
          <LivingEnvironment>Наземно-воздушная</LivingEnvironment>
          <Lifestyle>Дневной</Lifestyle>
          <HoofSize>8</HoofSize>
          <HornsSize>8</HornsSize>
        </Artiodactyl>
      </Value>
    </Point>
  </Items>
</MyNewCollectionOfStringAnimal>